telegrampx/__init__.py
telegrampx/bot.py
telegrampx-1.3.0.dist-info/METADATA
telegrampx-1.3.0.dist-info/WHEEL
telegrampx-1.3.0.dist-info/top_level.txt
telegrampx-1.3.0.dist-info/RECORD
