Metadata-Version: 2.1
Name: telegrampx
Version: 1.3.0
Summary: یک کتابخانه فوق سریع برای ربات تلگرام
Home-page: https://iliya8989.github.io/telegrampx/
Author: iliya kaviyani
Author-email: iliyakaviyani313@gmail.com
Classifier: Programming Language :: Python :: 3
Classifier: License :: OSI Approved :: MIT License
Classifier: Operating System :: OS Independent
Requires-Python: >=3.6
Requires-Dist: httpx
Requires-Dist: requests
